[{"cai":1,"cmtCount":0,"distance":0,"flag":1,"id":1,"placeDetail":"京沪高速进京31.6公里","placeName":"北京市应寺综合检查站","placeX":"116.735429","placeY":"39.644326","placeZone":1,"tel":"(010)80525400","type":1,"zan":0},{"cai":0,"cmtCount":0,"distance":0,"flag":1,"id":2,"placeDetail":"京哈高速路37.5公里处","placeName":"西集综合检查站","placeX":"116.910175","placeY":"39.805851","placeZone":1,"tel":"(010)68398140","type":1,"zan":0},{"cai":0,"cmtCount":0,"distance":0,"flag":1,"id":3,"placeDetail":"京港澳高速公路进京方向38公里","placeName":"京港澳高速窦店服务区办证处","placeX":"116.087852","placeY":"39.635838","placeZone":2,"tel":"(010)80318661","type":1,"zan":0},{"cai":40,"cmtCount":0,"distance":0,"flag":1,"id":4,"placeDetail":"107国道45公里处","placeName":"北京市琉璃河综合检查站","placeX":"116.02324","placeY":"39.598619","placeZone":2,"tel":"(010)89381242","type":1,"zan":17},{"cai":0,"cmtCount":0,"distance":0,"flag":0,"id":5,"placeDetail":"房易路10公里处","placeName":"房易路长沟综合检查站","placeX":"115.912612","placeY":"39.60021","placeZone":2,"tel":"(010)61361458","type":1,"zan":0},{"cai":0,"cmtCount":0,"distance":0,"flag":0,"id":6,"placeDetail":"漷县镇金三角开发区","placeName":"北京市觅子店综合检查站","placeX":"116.887068","placeY":"39.728594","placeZone":3,"tel":"(010)80566010","type":1,"zan":0},{"cai":0,"cmtCount":0,"distance":0,"flag":0,"id":7,"placeDetail":"通燕高速29.5公里处","placeName":"白庙综合检查站","placeX":"116.774481","placeY":"39.943303","placeZone":3,"tel":"(010)69591249","type":1,"zan":0},{"cai":0,"cmtCount":0,"distance":0,"flag":0,"id":8,"placeDetail":"京津高速公路进京方向32.5公里","placeName":"永乐综合检查站","placeX":"116.820911","placeY":"39.64834","placeZone":3,"tel":"(010)80586160","type":1,"zan":0},{"cai":0,"cmtCount":0,"distance":0,"flag":0,"id":9,"placeDetail":"G6京藏高速康庄桥出口附近 ","placeName":"北京市康庄综合检查站","placeX":"115.90143","placeY":"40.363782","placeZone":4,"tel":"(010)61164794","type":1,"zan":0},{"cai":0,"cmtCount":0,"distance":0,"flag":0,"id":10,"placeDetail":"109国道59.4公里","placeName":"北京市芹峪口综合检查站","placeX":"115.882569","placeY":"40.044341","placeZone":5,"tel":"(010)61830183","type":1,"zan":0},{"cai":0,"cmtCount":0,"distance":0,"flag":0,"id":11,"placeDetail":"京加路95公里处","placeName":"汤河口综合检查站","placeX":"116.646638","placeY":"40.738908","placeZone":6,"tel":"(010)89671245","type":1,"zan":0},{"cai":0,"cmtCount":0,"distance":0,"flag":0,"id":12,"placeDetail":"平三路6.2公里","placeName":"大旺务综合检查站","placeX":"117.112676","placeY":"40.094518","placeZone":7,"tel":"(010)69991279","type":1,"zan":0},{"cai":0,"cmtCount":0,"distance":0,"flag":0,"id":13,"placeDetail":"京平高速67公里处","placeName":"夏各庄办证处","placeX":"117.210273","placeY":"40.134308","placeZone":7,"tel":"(010)60912030","type":1,"zan":0},{"cai":0,"cmtCount":0,"distance":0,"flag":0,"id":14,"placeDetail":"204省道附近","placeName":"北京市马坊综合检查站","placeX":"117.017731","placeY":"40.040309","placeZone":7,"tel":"(010)69991279","type":1,"zan":0},{"cai":0,"cmtCount":0,"distance":0,"flag":0,"id":15,"placeDetail":"上堡子村 ","placeName":"北京市上堡子综合检查站","placeX":"117.376483","placeY":"40.185031","placeZone":7,"tel":"(010)69991279","type":1,"zan":0},{"cai":0,"cmtCount":0,"distance":0,"flag":0,"id":16,"placeDetail":"密兴路35公里处","placeName":"北京市墙子路综合检查站","placeX":"117.224449","placeY":"40.427212","placeZone":8,"tel":"(010)69041895","type":1,"zan":0},{"cai":0,"cmtCount":0,"distance":0,"flag":0,"id":17,"placeDetail":"京承高速路124.5公里处","placeName":"司马办证处","placeX":"117.239316","placeY":"40.617999","placeZone":8,"tel":"(010)69041895","type":1,"zan":0},{"cai":0,"cmtCount":0,"distance":0,"flag":0,"id":18,"placeDetail":"101国道103公里处","placeName":"松树峪办证处","placeX":"117.155136","placeY":"40.561723","placeZone":8,"tel":"(010)69036473","type":1,"zan":0},{"cai":0,"cmtCount":0,"distance":0,"flag":0,"id":19,"placeDetail":"北京市延庆县西官路","placeName":"北京市西康综合检查站","placeX":"115.879619","placeY":"40.365362","placeZone":9,"tel":"(010)61161538","type":1,"zan":0},{"cai":0,"cmtCount":0,"distance":0,"flag":0,"id":20,"placeDetail":"滦赤路157.2公里","placeName":"白河堡综合检查站","placeX":"116.171893","placeY":"40.660274","placeZone":9,"tel":"(010)60152037","type":1,"zan":0},{"cai":0,"cmtCount":0,"distance":0,"flag":0,"id":21,"placeDetail":"110国道92.4公里处","placeName":"张山营综合检查站","placeX":"115.80166","placeY":"40.448999","placeZone":9,"tel":"(010)69111015","type":1,"zan":0},{"cai":0,"cmtCount":0,"distance":0,"flag":0,"id":22,"placeDetail":"104国道45公里 ","placeName":"104国道凤河营办证处","placeX":"116.699392","placeY":"39.617721","placeZone":10,"tel":"(010)80202567","type":1,"zan":0},{"cai":0,"cmtCount":0,"distance":0,"flag":0,"id":23,"placeDetail":"京哈高速路37.5公里处","placeName":"西集综合检查站","placeX":"23.23223","placeY":"23.23223","placeZone":10,"tel":"(010)68398140","type":1,"zan":0},{"cai":0,"cmtCount":0,"distance":0,"flag":0,"id":24,"placeDetail":"106公路38公里处","placeName":"榆垡办证处","placeX":"116.331177","placeY":"39.511157","placeZone":10,"tel":"(010)89213399","type":1,"zan":0}]